{
  "name_en": "Sakura Miko",
  "status": "Active",
  "group": "hololive/gen-0",
  "YouTube": "https://www.youtube.com/channel/UC-hM6YJuNYVAmUWxeIr9FeA?sub_confirmation=1",
  "X": "https://twitter.com/sakuramiko35",
  "Twitch": "https://www.twitch.tv/sakuramiko_hololive",
  "Tik Tok": "https://www.tiktok.com/@sakuramiko_hololive",
  "Song Playlist": "https://youtube.com/playlist?list=PLMF8NocLqJttJCIiUCkNXx6jW4dAYfz5G&si=g2i8rWGyqBy61a9x",
  "MMD": "https://3d.nicovideo.jp/works/td74928",
  "MMD(2)": "https://3d.nicovideo.jp/works/td74930"
}